federated_glm/__init__.py
federated_glm/core.py
federated_glm/evaluation.py
federated_glm/federation.py
federated_glm/personalized.py
federated_glm/utils.py
federated_glm-0.2.0.dist-info/licenses/LICENSE
federated_glm-0.2.0.dist-info/METADATA
federated_glm-0.2.0.dist-info/WHEEL
federated_glm-0.2.0.dist-info/top_level.txt
federated_glm-0.2.0.dist-info/RECORD
